<?xml version="1.0" encoding="UTF-8"?>
<territory-type>
    <territory color="1181565196">
        <zone name="Graze" smin="0" smax="0" dmin="1" dmax="1" x="5314.25" z="10770.8" r="150"/>
        <zone name="Graze" smin="0" smax="0" dmin="1" dmax="1" x="5283" z="13100" r="150"/>
        <zone name="Graze" smin="0" smax="0" dmin="1" dmax="1" x="4560" z="14374" r="150"/>
        <zone name="Graze" smin="0" smax="0" dmin="1" dmax="1" x="6110" z="13211" r="150"/>
        <zone name="Graze" smin="0" smax="0" dmin="1" dmax="1" x="7268" z="12851" r="150"/>
        <zone name="Graze" smin="0" smax="0" dmin="1" dmax="1" x="7481" z="13903" r="150"/>
        <zone name="Graze" smin="0" smax="0" dmin="1" dmax="1" x="8299" z="13687" r="150"/>
        <zone name="Graze" smin="0" smax="0" dmin="1" dmax="1" x="8888" z="12905" r="150"/>
        <zone name="Graze" smin="0" smax="0" dmin="1" dmax="1" x="8993" z="13461" r="150"/>
        <zone name="Graze" smin="0" smax="0" dmin="1" dmax="1" x="5520" z="14055" r="150"/>
        <zone name="Graze" smin="0" smax="0" dmin="1" dmax="1" x="4753" z="12354" r="150"/>
        <zone name="Graze" smin="0" smax="0" dmin="1" dmax="1" x="5715" z="11787" r="150"/>
        <zone name="Graze" smin="0" smax="0" dmin="1" dmax="1" x="6968" z="12102" r="150"/>
        <zone name="Graze" smin="0" smax="0" dmin="1" dmax="1" x="6473" z="14025" r="150"/>
        <zone name="Graze" smin="0" smax="0" dmin="1" dmax="1" x="3545" z="12050" r="150"/>
        <zone name="Graze" smin="0" smax="0" dmin="1" dmax="1" x="4725" z="13280" r="150"/>
        <zone name="Graze" smin="0" smax="0" dmin="1" dmax="1" x="6265" z="12740" r="150"/>
        <zone name="Graze" smin="0" smax="0" dmin="1" dmax="1" x="6210" z="11690" r="150"/>
        <zone name="Graze" smin="0" smax="0" dmin="1" dmax="1" x="7020" z="10460" r="150"/>
        <zone name="Graze" smin="0" smax="0" dmin="1" dmax="1" x="3240" z="13275" r="150"/>
    </territory>
</territory-type>
